earnbase_common-0.2.7.dist-info/METADATA
earnbase_common-0.2.7.dist-info/WHEEL
earnbase_common-0.2.7.dist-info/entry_points.txt
earnbase_common-0.2.7.dist-info/licenses/LICENSE
earnbase_common/config/__init__.py
earnbase_common/config/base.py
earnbase_common/containers/__init__.py
earnbase_common/database/__init__.py
earnbase_common/database/mongodb.py
earnbase_common/database/repository.py
earnbase_common/errors/__init__.py
earnbase_common/errors/exceptions.py
earnbase_common/errors/handlers.py
earnbase_common/http/__init__.py
earnbase_common/http/base.py
earnbase_common/logging/__init__.py
earnbase_common/logging/config.py
earnbase_common/logging/logger.py
earnbase_common/logging/processors.py
earnbase_common/metrics/__init__.py
earnbase_common/metrics/metrics.py
earnbase_common/middleware/__init__.py
earnbase_common/middleware/request_tracking.py
earnbase_common/middleware/security.py
earnbase_common/models/__init__.py
earnbase_common/models/aggregate.py
earnbase_common/models/domain_event.py
earnbase_common/redis/__init__.py
earnbase_common/redis/client.py
earnbase_common/responses/__init__.py
earnbase_common/responses/base.py
earnbase_common/responses/json.py
earnbase_common/retry/__init__.py
earnbase_common/security/__init__.py
earnbase_common/security/jwt.py
earnbase_common/security/password.py
earnbase_common/security/policy.py
earnbase_common/value_objects/__init__.py
earnbase_common/value_objects/address.py
earnbase_common/value_objects/email.py
earnbase_common/value_objects/money.py
earnbase_common/value_objects/password.py
earnbase_common/value_objects/phone.py
earnbase_common/value_objects/token.py
earnbase_common-0.2.7.dist-info/RECORD
