Metadata-Version: 2.1
Name: earnbase-common
Version: 0.2.7
Summary: Common utilities for Earnbase services
Keywords: logging,utilities,microservices,fastapi,mongodb,redis
Author-Email: Earnbase Team <dev@earnbase.io>
License: MIT
Classifier: Development Status :: 4 - Beta
Classifier: Intended Audience :: Developers
Classifier: License :: OSI Approved :: MIT License
Classifier: Programming Language :: Python :: 3
Classifier: Programming Language :: Python :: 3.9
Classifier: Programming Language :: Python :: 3.10
Classifier: Programming Language :: Python :: 3.11
Classifier: Topic :: Software Development :: Libraries :: Python Modules
Classifier: Topic :: System :: Logging
Classifier: Framework :: FastAPI
Classifier: Operating System :: OS Independent
Classifier: Typing :: Typed
Project-URL: Homepage, https://github.com/earnbaseio/earnbase-common
Project-URL: Documentation, https://github.com/earnbaseio/earnbase-common#readme
Project-URL: Source Code, https://github.com/earnbaseio/earnbase-common
Project-URL: Bug Tracker, https://github.com/earnbaseio/earnbase-common/issues
Project-URL: Changelog, https://github.com/earnbaseio/earnbase-common/blob/main/CHANGELOG.md
Requires-Python: >=3.9
Requires-Dist: pydantic>=2.5.2
Requires-Dist: fastapi>=0.104.1
Requires-Dist: motor>=3.3.2
Requires-Dist: redis>=5.0.1
Requires-Dist: structlog>=23.2.0
Requires-Dist: prometheus-client>=0.19.0
Requires-Dist: pyjwt>=2.8.0
Requires-Dist: pyyaml>=6.0.1
Requires-Dist: httpx>=0.26.0
Requires-Dist: bcrypt>=4.2.1
Requires-Dist: pytest-asyncio>=0.25.2
Requires-Dist: anyio>=4.8.0
Requires-Dist: tenacity>=8.2.3
Requires-Dist: dependency-injector>=4.41.0
